fcs_package/__init__.py
fcs_package/fcs_last_digit.py
fcs_package/fcs_square.py
fcs_package-1.0.1.dist-info/METADATA
fcs_package-1.0.1.dist-info/WHEEL
fcs_package-1.0.1.dist-info/top_level.txt
fcs_package-1.0.1.dist-info/RECORD
