Metadata-Version: 2.4
Name: fcs_package
Version: 1.0.1
Summary: Last digit of squares
Author: Csaba
Requires-Dist: numpy
Requires-Dist: pandas
